[
    {
        "first_name": "Roger",
        "last_name": "Rabbit",
        "role_id": 33,
        "manager_id": 702
    },
    {
        "first_name": "Bugs",
        "last_name": "Bunny",
        "role_id": 33,
        "manager_id": null
    },
    {
        "first_name": "Conrad",
        "last_name": "Capsin",
        "role_id": 22,
        "manager_id": 122
    },
    {
        "first_name": "Hulk",
        "last_name": "Hogan",
        "role_id": 111,
        "manager_id": null
    },
    {
        "first_name": "Barbra",
        "last_name": "Gordan",
        "role_id": 112,
        "manager_id": null
    }
]